dhinchakmasti
