Metadata-Version: 1.0
Name: DhinchakAshvary
Version: 1.0.1
Summary: my first python library
Home-page: UNKNOWN
Author: UNKNOWN
Author-email: UNKNOWN
License: UNKNOWN
Platform: UNKNOWN
